decoratorsutility/__init__.py
decoratorsutility/_routing.py
decoratorsutility/_version.py
decoratorsutility/decorators.py
decoratorsutility/utils/__init__.py
decoratorsutility/utils/errors.py
decoratorsutility/utils/logs.py
decoratorsutility-1.0.0.dist-info/LICENSE
decoratorsutility-1.0.0.dist-info/METADATA
decoratorsutility-1.0.0.dist-info/WHEEL
decoratorsutility-1.0.0.dist-info/top_level.txt
decoratorsutility-1.0.0.dist-info/RECORD
