Metadata-Version: 2.1
Name: decoratorsutility
Version: 1.0.0
Summary: decorators utility
Author: anglisanosa
Author-email: marcanglisano@gmail.com
Project-URL: Documentation, https://anglisanosa.github.io/decoratorsutility/
Project-URL: Bug Reports, https://github.com/anglisanosa/decoratorsutility/issues
Project-URL: Source, https://github.com/anglisanosa/decoratorsutility
Classifier: Programming Language :: Python :: 3
Classifier: Operating System :: OS Independent
Requires-Python: >=3.8
License-File: LICENSE
Requires-Dist: pathutility ~=1.0.0
Requires-Dist: pygogo ~=1.3.0
